statilib/__init__.py
statilib/formula.py
statilib/unit_tests.py
statilib-0.1.0.dist-info/METADATA
statilib-0.1.0.dist-info/WHEEL
statilib-0.1.0.dist-info/top_level.txt
statilib-0.1.0.dist-info/RECORD
