Metadata-Version: 2.4
Name: statilib
Version: 0.1.0
Summary: A simple statistics library
Author: Abdulrahman F. Alosaimi
Requires-Python: >=3.6
Dynamic: author
Dynamic: description
Dynamic: description-content-type
Dynamic: requires-python
Dynamic: summary
